MANIFEST.in
README.md
setup.py
openpifpafwebdemo/__init__.py
openpifpafwebdemo/base.html
openpifpafwebdemo/client.html
openpifpafwebdemo/index.html
openpifpafwebdemo/processor.py
openpifpafwebdemo/server.py
openpifpafwebdemo.egg-info/PKG-INFO
openpifpafwebdemo.egg-info/SOURCES.txt
openpifpafwebdemo.egg-info/dependency_links.txt
openpifpafwebdemo.egg-info/requires.txt
openpifpafwebdemo.egg-info/top_level.txt
openpifpafwebdemo/static/analysis.js
openpifpafwebdemo/static/analysis.js.map
openpifpafwebdemo/static/clientside.js
openpifpafwebdemo/static/clientside.js.map
openpifpafwebdemo/static/favicon.ico
openpifpafwebdemo/static/frontend.js
openpifpafwebdemo/static/frontend.js.map
openpifpafwebdemo/static/logo.svg
openpifpafwebdemo/static/style.css