Metadata-Version: 2.1
Name: openpifpafwebdemo
Version: 0.9.0
Summary: Web-browser demo for openpifpaf.
Home-page: https://github.com/vita-epfl/openpifpafwebdemo
Author: Sven Kreiss
Author-email: research@svenkreiss.com
License: MIT
Platform: UNKNOWN
Provides-Extra: test
